mmdatascienceutils/__init__.py
mmdatascienceutils/plots.py
mmdatascienceutils-0.0.1.dist-info/LICENSE
mmdatascienceutils-0.0.1.dist-info/METADATA
mmdatascienceutils-0.0.1.dist-info/WHEEL
mmdatascienceutils-0.0.1.dist-info/top_level.txt
mmdatascienceutils-0.0.1.dist-info/RECORD
